easy_api/easy_api.py
easy_api-0.1.dist-info/LICENSE.txt
easy_api-0.1.dist-info/METADATA
easy_api-0.1.dist-info/WHEEL
easy_api-0.1.dist-info/top_level.txt
easy_api-0.1.dist-info/RECORD
