Metadata-Version: 2.1
Name: easy-api
Version: 0.1
Summary: a easy-to-use library of APIs
Home-page: https://github.com/mime-r/easy_api
Author: Samuel Cheng
Author-email: samuelcheng000@gmail.com
License: MIT
Download-URL: https://github.com/mime-r/easy_api/archive/refs/tags/0.1.tar.gz
Keywords: api,apis,easy
Platform: UNKNOWN
Classifier: Development Status :: 3 - Alpha
Classifier: Intended Audience :: Developers
Classifier: Topic :: Software Development :: Build Tools
Classifier: License :: OSI Approved :: MIT License
Classifier: Programming Language :: Python :: 3
Classifier: Programming Language :: Python :: 3.4
Classifier: Programming Language :: Python :: 3.5
Classifier: Programming Language :: Python :: 3.6
Classifier: Programming Language :: Python :: 3.7
Classifier: Programming Language :: Python :: 3.8
Classifier: Programming Language :: Python :: 3.9
License-File: LICENSE.txt
Requires-Dist: requests
Requires-Dist: json
